{"abiSet":"手机","apkTemplatePath":"C:\\Users\\13983\\Desktop\\ec.apk","appName":"自动签到","autoActive":"是","auto_run_boot_script":"否","auto_run_script":"否","auto_start_service":"否","ctrl_float_window":"否","enc_pwd":"","iconPath":"D:\\WorkSpace\\AutoJS\\EC.SignIn\\src\\res\\app.png","imageModule":"否","log_float_window":"否","logo_path":"","mainColor":"","pkgName":"io.gcdd1993.ec.signin","pkg_source_option":"js","producer_name":"","running_mode":"无障碍模式","show_header_bar":"否","show_start_btn":"是","show_system_setting_btn":"否","version_code":"100","version_name":"1.0.0"}